investpy/__init__.py
investpy/calculos.py
investpy/dados.py
investpy/visualizacao.py
investimentpyilton-1.0.1.dist-info/METADATA
investimentpyilton-1.0.1.dist-info/WHEEL
investimentpyilton-1.0.1.dist-info/top_level.txt
investimentpyilton-1.0.1.dist-info/RECORD
