Metadata-Version: 2.1
Name: investimentpyilton
Version: 1.0.1
Summary: Uma biblioteca para análise de investimentos
Home-page: https://github.com/jpardocimo/investimentpyilton
Author: Ailton Pardocimo Jr
Author-email: jpardocimo@gmail.com
License: MIT
Platform: UNKNOWN
